llm_fragments_repomix.py
llm_fragments_repomix-0.1.0.dist-info/licenses/LICENSE
llm_fragments_repomix-0.1.0.dist-info/METADATA
llm_fragments_repomix-0.1.0.dist-info/WHEEL
llm_fragments_repomix-0.1.0.dist-info/entry_points.txt
llm_fragments_repomix-0.1.0.dist-info/top_level.txt
llm_fragments_repomix-0.1.0.dist-info/RECORD
