Metadata-Version: 2.4
Name: llm-fragments-repomix
Version: 0.1.0
Summary: Load repository contents as LLM fragments using Repomix
Author: Amolith
License-Expression: Apache-2.0
Project-URL: Homepage, https://git.sr.ht/~amolith/llm-fragments-repomix
Project-URL: Changelog, https://git.sr.ht/~amolith/llm-fragments-repomix/refs
Project-URL: Issues, https://todo.sr.ht/~amolith/public-tracker
Requires-Python: >=3.9
License-File: LICENSE
Requires-Dist: llm
Provides-Extra: test
Requires-Dist: pytest; extra == "test"
Dynamic: license-file
